Metadata-Version: 2.1
Name: frasht
Version: 0.0.3
Summary: A library that makes Python development easier
Home-page: https://github.com/
Author: Frasht
Author-email: 3357099132@qq.com
License: MIT License
Keywords: ds caa
Platform: any
License-File: LICENSE.txt
